easybitcoinrpc/__init__.py
easybitcoinrpc/blockchain.py
easybitcoinrpc/control.py
easybitcoinrpc/data.py
easybitcoinrpc/generating.py
easybitcoinrpc/mining.py
easybitcoinrpc/network.py
easybitcoinrpc/raw_transactions.py
easybitcoinrpc/rpc.py
easybitcoinrpc/util.py
easybitcoinrpc/wallet.py
easybitcoinrpc-1.1.0.dist-info/LICENSE
easybitcoinrpc-1.1.0.dist-info/METADATA
easybitcoinrpc-1.1.0.dist-info/WHEEL
easybitcoinrpc-1.1.0.dist-info/top_level.txt
easybitcoinrpc-1.1.0.dist-info/RECORD
