Metadata-Version: 2.1
Name: easybitcoinrpc
Version: 1.1.0
Summary: Simple and easy to use library for Bitcoin RPC
Home-page: https://github.com/DorianKucharski/easybitcoinrpc
Author: Dorian Kucharski
Author-email: dorian.kucharski1@gmail.com
License: UNKNOWN
Platform: UNKNOWN
Classifier: Programming Language :: Python :: 3
Classifier: License :: OSI Approved :: MIT License
Classifier: Operating System :: OS Independent
Requires-Python: >=3.6
Requires-Dist: bitcoinrpc
Requires-Dist: cryptocompare
